{
  "id": "MAP_GALEFORCE_CLIFFS",
  "name": "GaleforceCliffs",
  "layout": "LAYOUT_GALEFORCE_CLIFFS",
  "music": "MUS_PL_WIFI_PLAZA",
  "region_map_section": "MAPSEC_GALEFORCE_CLIFF",
  "requires_flash": false,
  "weather": "WEATHER_NONE",
  "map_type": "MAP_TYPE_ROUTE",
  "allow_cycling": true,
  "allow_escaping": false,
  "allow_running": true,
  "show_map_name": true,
  "battle_scene": "MAP_BATTLE_SCENE_NORMAL",
  "connections": [
    {
      "map": "MAP_ROUTE125",
      "offset": -45,
      "direction": "down"
    }
  ],
  "object_events": [
    {
      "graphics_id": "OBJ_EVENT_GFX_SPECIES(TORNADUS)",
      "x": 7,
      "y": 16,
      "elevation": 0,
      "movement_type": "MOVEMENT_TYPE_NONE",
      "movement_range_x": 0,
      "movement_range_y": 0,
      "trainer_type": "TRAINER_TYPE_NONE",
      "trainer_sight_or_berry_tree_id": "0",
      "script": "BattleTornadus",
      "flag": "FLAG_TEMP_2"
    },
    {
      "graphics_id": "OBJ_EVENT_GFX_SPECIES(THUNDURUS)",
      "x": 19,
      "y": 16,
      "elevation": 0,
      "movement_type": "MOVEMENT_TYPE_NONE",
      "movement_range_x": 0,
      "movement_range_y": 0,
      "trainer_type": "TRAINER_TYPE_NONE",
      "trainer_sight_or_berry_tree_id": "0",
      "script": "BattleThundurus",
      "flag": "FLAG_TEMP_3"
    },
    {
      "graphics_id": "OBJ_EVENT_GFX_SPECIES(ENAMORUS)",
      "x": 13,
      "y": 19,
      "elevation": 0,
      "movement_type": "MOVEMENT_TYPE_NONE",
      "movement_range_x": 0,
      "movement_range_y": 0,
      "trainer_type": "TRAINER_TYPE_NONE",
      "trainer_sight_or_berry_tree_id": "0",
      "script": "BattleEnamorus",
      "flag": "FLAG_TEMP_4"
    },
    {
      "graphics_id": "OBJ_EVENT_GFX_SPECIES(LANDORUS)",
      "x": 13,
      "y": 6,
      "elevation": 0,
      "movement_type": "MOVEMENT_TYPE_NONE",
      "movement_range_x": 0,
      "movement_range_y": 0,
      "trainer_type": "TRAINER_TYPE_NONE",
      "trainer_sight_or_berry_tree_id": "0",
      "script": "BattleLandorus",
      "flag": "FLAG_TEMP_5"
    }
  ],
  "warp_events": [],
  "coord_events": [],
  "bg_events": []
}
