{
  "id": "MAP_MAUVE_HOLLOW_1",
  "name": "MauveHollow_1",
  "layout": "LAYOUT_MAUVE_HOLLOW_1",
  "music": "MUS_DP_OREBURGH_GATE",
  "region_map_section": "MAPSEC_MAUVE_HOLLOW",
  "requires_flash": false,
  "weather": "WEATHER_NONE",
  "map_type": "MAP_TYPE_UNDERGROUND",
  "allow_cycling": true,
  "allow_escaping": true,
  "allow_running": true,
  "show_map_name": true,
  "battle_scene": "MAP_BATTLE_SCENE_NORMAL",
  "connections": null,
  "object_events": [],
  "warp_events": [
    {
      "x": 24,
      "y": 16,
      "elevation": 0,
      "dest_map": "MAP_MAUVE_ISLAND_SOUTHEAST",
      "dest_warp_id": "0"
    },
    {
      "x": 4,
      "y": 3,
      "elevation": 0,
      "dest_map": "MAP_MAUVE_ISLAND_SOUTH",
      "dest_warp_id": "1"
    }
  ],
  "coord_events": [],
  "bg_events": []
}
